pywibeee/__init__.py
pywibeee/discovery.py
pywibeee/main.py
pywibeee-0.0.6.data/scripts/pywibeee
pywibeee-0.0.6.dist-info/LICENSE
pywibeee-0.0.6.dist-info/METADATA
pywibeee-0.0.6.dist-info/WHEEL
pywibeee-0.0.6.dist-info/entry_points.txt
pywibeee-0.0.6.dist-info/top_level.txt
pywibeee-0.0.6.dist-info/RECORD
