Metadata-Version: 2.1
Name: pywibeee
Version: 0.0.6
Summary: Command line interface (CLI) for WiBeee (old Mirubee) meter
Home-page: https://github.com/fquinto/pywibeee
Author: fquinto
Author-email: fquinto <fran.quinto@gmail.com>
License: Copyright (C) fquinto
Project-URL: Homepage, https://github.com/fquinto/pywibeee
Keywords: homeautomation,cli,interface,wibeee,mirubeee,energy meter,smart meter,hass
Classifier: License :: OSI Approved :: GNU General Public License v2 (GPLv2)
Classifier: Programming Language :: Python :: 3
Classifier: Operating System :: OS Independent
Classifier: Topic :: Home Automation
Classifier: Topic :: System :: Monitoring
Classifier: Topic :: System :: Shells
Classifier: Development Status :: 5 - Production/Stable
Classifier: Environment :: Console
Classifier: Intended Audience :: End Users/Desktop
Classifier: Intended Audience :: Developers
Requires-Python: >=3.7
License-File: LICENSE
Requires-Dist: xmltodict (>=0.13.0)
Requires-Dist: requests
Requires-Dist: aiohttp
Requires-Dist: httpx
